testOrganizer/CMDLog.py
testOrganizer/TestDecorator.py
testOrganizer/__init__.py
testOrganizer-0.0.7.dist-info/METADATA
testOrganizer-0.0.7.dist-info/WHEEL
testOrganizer-0.0.7.dist-info/top_level.txt
testOrganizer-0.0.7.dist-info/RECORD
