Metadata-Version: 2.1
Name: testOrganizer
Version: 0.0.7
Summary: Organize tests and show results
Home-page: https://github.com/smirad91/testOrganize
Author: smirad91
Author-email: smirad91@gmail.com
License: UNKNOWN
Project-URL: Bug Tracker, https://github.com/smirad91/testOrganize/issues
Keywords: test,before,after,automation,result,console,output
Platform: UNKNOWN
Classifier: Programming Language :: Python :: 3
Classifier: License :: OSI Approved :: MIT License
Classifier: Operating System :: Microsoft :: Windows
Requires-Dist: tabulate
